{
  "knowledge_node_id": "node-31",
  "kind": "fill",
  "content": "<pre class=\"CodeRay\"><code class=\"javascript\"><span class=\"keyword\">var</span> txt = <span class=\"string\"><span class=\"delimiter\">\"</span><span class=\"content\">a,b,c,d,e</span><span class=\"delimiter\">\"</span></span>;\n<span class=\"keyword\">var</span> arr = txt.split( [%] );\nalert(arr.length == <span class=\"integer\">5</span>)\n</code></pre>\n上面的代码运行结果如下\n<img src=\"file:///android_asset/questions/node_31/14.jpg\">\n请用下面的选项补全代码\n",
  "choices": [
    "\"\"",
    "\" \" ",
    "\",\"",
    "\"|\""
  ],
  "answer": "\",\""
}